reload.py
setup.py
reload.egg-info/PKG-INFO
reload.egg-info/SOURCES.txt
reload.egg-info/dependency_links.txt
reload.egg-info/entry_points.txt
reload.egg-info/requires.txt
reload.egg-info/top_level.txt