Metadata-Version: 1.1
Name: reload
Version: 0.5
Summary: Reload a program if any file in current directory changes.
Home-page: https://github.com/loomchild/reload
Author: Jarek Lipski
Author-email: pub@loomchild.net
License: MIT
Keywords: reload server
Platform: UNKNOWN
Classifier: Development Status :: 4 - Beta
Classifier: Topic :: Utilities
Classifier: License :: OSI Approved :: MIT License
